flake2lint/__init__.py
flake2lint/__main__.py
flake2lint/py.typed
flake2lint-0.4.3.dist-info/LICENSE
flake2lint-0.4.3.dist-info/METADATA
flake2lint-0.4.3.dist-info/WHEEL
flake2lint-0.4.3.dist-info/entry_points.txt
flake2lint-0.4.3.dist-info/RECORD
