Metadata-Version: 2.1
Name: flake2lint
Version: 0.4.3
Summary: Tool and pre-commit hook to augment Flake8 noqa comments with PyLint comments.
Author-email: Dominic Davis-Foster <dominic@davis-foster.co.uk>
License: MIT
Keywords: flake8,pre-commit,pylint
Home-page: https://github.com/domdfcoding/flake2lint
Project-URL: Issue Tracker, https://github.com/domdfcoding/flake2lint/issues
Project-URL: Source Code, https://github.com/domdfcoding/flake2lint
Project-URL: Documentation, https://flake2lint.readthedocs.io/en/latest
Platform: Windows
Platform: macOS
Platform: Linux
Classifier: Development Status :: 4 - Beta
Classifier: Environment :: Console
Classifier: Framework :: Flake8
Classifier: Intended Audience :: Developers
Classifier: License :: OSI Approved :: MIT License
Classifier: Operating System :: OS Independent
Classifier: Programming Language :: Python
Classifier: Programming Language :: Python :: 3 :: Only
Classifier: Programming Language :: Python :: 3.6
Classifier: Programming Language :: Python :: 3.7
Classifier: Programming Language :: Python :: 3.8
Classifier: Programming Language :: Python :: 3.9
Classifier: Programming Language :: Python :: 3.10
Classifier: Programming Language :: Python :: 3.11
Classifier: Programming Language :: Python :: Implementation :: CPython
Classifier: Programming Language :: Python :: Implementation :: PyPy
Classifier: Typing :: Typed
Requires-Python: >=3.6
Requires-Dist: click>=7.1.2
Requires-Dist: consolekit>=1.0.1
Requires-Dist: domdf-python-tools>=2.1.0
Requires-Dist: flake8>=3.8.4
